alibabacloud_umeng_finplus20220913/__init__.py
alibabacloud_umeng_finplus20220913/client.py
alibabacloud_umeng_finplus20220913/models/__init__.py
alibabacloud_umeng_finplus20220913/models/_build_sts_ak2request.py
alibabacloud_umeng_finplus20220913/models/_build_sts_ak2response.py
alibabacloud_umeng_finplus20220913/models/_build_sts_ak2response_body.py
alibabacloud_umeng_finplus20220913/models/_build_sts_akrequest.py
alibabacloud_umeng_finplus20220913/models/_build_sts_akresponse.py
alibabacloud_umeng_finplus20220913/models/_build_sts_akresponse_body.py
alibabacloud_umeng_finplus20220913/models/_cancel_task_2request.py
alibabacloud_umeng_finplus20220913/models/_cancel_task_2response.py
alibabacloud_umeng_finplus20220913/models/_cancel_task_2response_body.py
alibabacloud_umeng_finplus20220913/models/_cancel_task_request.py
alibabacloud_umeng_finplus20220913/models/_cancel_task_response.py
alibabacloud_umeng_finplus20220913/models/_cancel_task_response_body.py
alibabacloud_umeng_finplus20220913/models/_create_compute_task_2request.py
alibabacloud_umeng_finplus20220913/models/_create_compute_task_2response.py
alibabacloud_umeng_finplus20220913/models/_create_compute_task_2response_body.py
alibabacloud_umeng_finplus20220913/models/_create_compute_task_request.py
alibabacloud_umeng_finplus20220913/models/_create_compute_task_response.py
alibabacloud_umeng_finplus20220913/models/_create_compute_task_response_body.py
alibabacloud_umeng_finplus20220913/models/_create_data_set_2request.py
alibabacloud_umeng_finplus20220913/models/_create_data_set_2response.py
alibabacloud_umeng_finplus20220913/models/_create_data_set_2response_body.py
alibabacloud_umeng_finplus20220913/models/_create_data_set_request.py
alibabacloud_umeng_finplus20220913/models/_create_data_set_response.py
alibabacloud_umeng_finplus20220913/models/_create_data_set_response_body.py
alibabacloud_umeng_finplus20220913/models/_create_instance_task_request.py
alibabacloud_umeng_finplus20220913-1.1.0.dist-info/LICENSE
alibabacloud_umeng_finplus20220913-1.1.0.dist-info/METADATA
alibabacloud_umeng_finplus20220913-1.1.0.dist-info/WHEEL
alibabacloud_umeng_finplus20220913-1.1.0.dist-info/top_level.txt
alibabacloud_umeng_finplus20220913-1.1.0.dist-info/RECORD
